preqlt/__init__.py
preqlt/constants.py
preqlt/core.py
preqlt/enums.py
preqlt/exceptions.py
preqlt/graph.py
preqlt/dbt/__init__.py
preqlt/dbt/config.py
preqlt/dbt/generate_dbt.py
preqlt/dbt/run_dbt.py
preqlt/scripts/__init__.py
preqlt/scripts/main.py
pypreqlt-0.0.3.dist-info/LICENSE.md
pypreqlt-0.0.3.dist-info/METADATA
pypreqlt-0.0.3.dist-info/WHEEL
pypreqlt-0.0.3.dist-info/entry_points.txt
pypreqlt-0.0.3.dist-info/top_level.txt
pypreqlt-0.0.3.dist-info/RECORD
