Metadata-Version: 2.1
Name: pypreqlt
Version: 0.0.3
Summary: Enhanced PreQL for common ETL needs.
Home-page: 
Author: 
Author-email: preql-community@gmail.com
Classifier: Programming Language :: Python
Classifier: Programming Language :: Python :: 3
Classifier: Programming Language :: Python :: 3.9
Classifier: Programming Language :: Python :: 3.10
Classifier: Programming Language :: Python :: 3.11
Classifier: Programming Language :: Python :: 3.12
Classifier: Programming Language :: Python :: 3.13
License-File: LICENSE.md
Requires-Dist: pypreql >=0.0.1.96
Requires-Dist: dbt-core
Provides-Extra: bigquery
Requires-Dist: dbt-bigquery ; extra == 'bigquery'
Provides-Extra: duckdb
Requires-Dist: dbt-duckdb ; extra == 'duckdb'
